__init__.py
mysql_cloud.py
zx_mysql-0.1.0.dist-info/METADATA
zx_mysql-0.1.0.dist-info/WHEEL
zx_mysql-0.1.0.dist-info/top_level.txt
zx_mysql-0.1.0.dist-info/RECORD
